{
  "name": "Fanny Black",
  "age": 48,
  "address": {
    "street": "Litdag Junction",
    "city": "Iswijnob",
    "state": "WY",
    "zip": "81193"
  },
  "contact": {
    "phone": "(808) 405-8374",
    "servicePhone": "800852954"
  },
  "birthday": "1984-05-12T05:40:31.507Z",
  "ip": "79.21.66.55",
  "foo": "bar",
  "profile": {
    "about": "Doakesa zubsetno hevajwic pinti jebel ho joc hacuf uk guwuhu bubpozhu fimsajbip ogvalfu rezo uwideddu nobo akjami. Olokoder mavut lagzuc culzizrut zojecag nozkil afiuhfij reha wi otuzuvde atuturhig daecabe tezcaapi sovjapan gegino zeroco jenhujnev casivo. Di vu tukezogi jej ugecig udkez tupojkon novica vom cogujuv obuluovu bah ip neljuug.",
    "bio": "Ha ejipik zatbamac hor favikisen aricuke ven hi orza hifaw dedu pude. Ob hokmi do koczi gagjo gas kopesasu wusow hufkawwe citev hi ko ecmi eba. Sucud nebapi petvucdu dun foj la ulkihof re uk sudumpic pu hadahi peram rihzi buuse tic. Ri se hebezic na dakzob cu rus kef vuv depazti vo ujavu is rapol azla of ticlove. Ne rumlivmib emu jebiv idi refoja rahus pakvachow mo fa jore arudel fojos kujop vuawejo kubfoje joj. Jeplisseb bipto avak lauzpu bib hah durebil ulac taz wojocu no fagabbo optinni."
  },
  "apiKey": "d7d1f8cc08a0da0830c2e8e9bfe4274ae15935fb217e1c865be419f437f8addd",
  "currency": {
    "code": "OMR",
    "name": "Oman Rial"
  }
}